contextdict/__init__.py
contextdict/core.py
contextdict-0.1.1.dist-info/METADATA
contextdict-0.1.1.dist-info/WHEEL
contextdict-0.1.1.dist-info/top_level.txt
contextdict-0.1.1.dist-info/RECORD
