Metadata-Version: 2.1
Name: contextdict
Version: 0.1.1
Summary: A context-aware in-memory dictionary with Redis support, TTLs, and versioning.
Author: Yerram Mahendra Reddy
Author-email: yerram.mahi@gmail.com
Classifier: Programming Language :: Python :: 3
Classifier: License :: OSI Approved :: MIT License
Classifier: Operating System :: OS Independent
Requires-Python: >=3.7
Requires-Dist: redis >=4.0.0
